bittrade_kraken_rest/__init__.py
bittrade_kraken_rest/connection/__init__.py
bittrade_kraken_rest/connection/nonce.py
bittrade_kraken_rest/connection/observable.py
bittrade_kraken_rest/connection/result.py
bittrade_kraken_rest/connection/session.py
bittrade_kraken_rest/endpoints/__init__.py
bittrade_kraken_rest/endpoints/private/__init__.py
bittrade_kraken_rest/endpoints/private/account_balance.py
bittrade_kraken_rest/endpoints/private/add_order.py
bittrade_kraken_rest/endpoints/private/add_order_batch.py
bittrade_kraken_rest/endpoints/private/cancel_all.py
bittrade_kraken_rest/endpoints/private/cancel_order.py
bittrade_kraken_rest/endpoints/private/cancel_order_batch.py
bittrade_kraken_rest/endpoints/private/extended_balance.py
bittrade_kraken_rest/endpoints/private/open_orders.py
bittrade_kraken_rest/endpoints/private/query_order.py
bittrade_kraken_rest/endpoints/private/status_of_recent_deposits.py
bittrade_kraken_rest/endpoints/private/status_of_recent_withdrawals.py
bittrade_kraken_rest/endpoints/private/trade_balance.py
bittrade_kraken_rest/endpoints/private/trade_history.py
bittrade_kraken_rest/endpoints/private/websockets_token.py
bittrade_kraken_rest/endpoints/private/withdraw_funds.py
bittrade_kraken_rest/endpoints/private/withdrawal_addresses.py
bittrade_kraken_rest/endpoints/private/withdrawal_info.py
bittrade_kraken_rest/endpoints/private/withdrawal_methods.py
bittrade_kraken_rest/endpoints/public/__init__.py
bittrade_kraken_rest/endpoints/public/server_time.py
bittrade_kraken_rest/endpoints/public/system_status.py
bittrade_kraken_rest/endpoints/public/ticker.py
bittrade_kraken_rest/endpoints/raw.py
bittrade_kraken_rest/exceptions/__init__.py
bittrade_kraken_rest/exceptions/error.py
bittrade_kraken_rest/models/__init__.py
bittrade_kraken_rest/models/message.py
bittrade_kraken_rest/models/order.py
bittrade_kraken_rest/models/private/__init__.py
bittrade_kraken_rest/models/private/trade_balance.py
bittrade_kraken_rest/models/request.py
bittrade_kraken_rest-0.13.15.dist-info/WHEEL
bittrade_kraken_rest-0.13.15.dist-info/METADATA
bittrade_kraken_rest-0.13.15.dist-info/RECORD
