Metadata-Version: 2.1
Name: bittrade-kraken-rest
Version: 0.13.15
Summary: Kraken REST library
Home-page: https://github.com/TechSpaceAsia/bittrade-kraken-rest
License: MIT
Author: Matt Kho
Author-email: matt@techspace.asia
Requires-Python: >=3.10,<4.0
Classifier: Development Status :: 3 - Alpha
Classifier: Intended Audience :: Developers
Classifier: License :: OSI Approved :: MIT License
Classifier: Programming Language :: Python :: 3
Classifier: Programming Language :: Python :: 3.10
Classifier: Programming Language :: Python :: 3.11
Classifier: Topic :: Office/Business :: Financial :: Investment
Classifier: Topic :: Software Development :: Libraries :: Python Modules
Requires-Dist: orjson (>=3.8.3,<4.0.0)
Requires-Dist: pydantic (>=1.10.4,<2.0.0)
Requires-Dist: reactivex (>=4.0.4,<5.0.0)
Requires-Dist: requests (>=2.28.1,<3.0.0)
Project-URL: Repository, https://github.com/TechSpaceAsia/bittrade-kraken-rest
